{
W041:{
"code":"W041",
"count":45,
"detail":[
{"id":"(error)","raw":"Use '{a}' to compare with '{b}'.","code":"W041","evidence":"          if (null != nd.children[l])","line":85,"character":20,"scope":"(main)","a":"!==","b":"null","reason":"Use '!==' to compare with 'null'."},
{"id":"(error)","raw":"Use '{a}' to compare with '{b}'.","code":"W041","evidence":"        if (null == brch)","line":100,"character":18,"scope":"(main)","a":"===","b":"null","reason":"Use '===' to compare with 'null'."},
{"id":"(error)","raw":"Use '{a}' to compare with '{b}'.","code":"W041","evidence":"        while (null != nd)","line":111,"character":21,"scope":"(main)","a":"!==","b":"null","reason":"Use '!==' to compare with 'null'."},
{"id":"(error)","raw":"Use '{a}' to compare with '{b}'.","code":"W041","evidence":"          if (null == ndch)","line":114,"character":20,"scope":"(main)","a":"===","b":"null","reason":"Use '===' to compare with 'null'."},
{"id":"(error)","raw":"Use '{a}' to compare with '{b}'.","code":"W041","evidence":"        if (null == brch)","line":165,"character":18,"scope":"(main)","a":"===","b":"null","reason":"Use '===' to compare with 'null'."},
{"id":"(error)","raw":"Use '{a}' to compare with '{b}'.","code":"W041","evidence":"        while (null != nd)","line":187,"character":21,"scope":"(main)","a":"!==","b":"null","reason":"Use '!==' to compare with 'null'."},
{"id":"(error)","raw":"Use '{a}' to compare with '{b}'.","code":"W041","evidence":"          if (null == ndch)","line":190,"character":20,"scope":"(main)","a":"===","b":"null","reason":"Use '===' to compare with 'null'."},
{"id":"(error)","raw":"Use '{a}' to compare with '{b}'.","code":"W041","evidence":"        if (null == brch)","line":230,"character":18,"scope":"(main)","a":"===","b":"null","reason":"Use '===' to compare with 'null'."},
{"id":"(error)","raw":"Use '{a}' to compare with '{b}'.","code":"W041","evidence":"          if (null != f)","line":238,"character":20,"scope":"(main)","a":"!==","b":"null","reason":"Use '!==' to compare with 'null'."},
{"id":"(error)","raw":"Use '{a}' to compare with '{b}'.","code":"W041","evidence":"                while (null != f)","line":246,"character":29,"scope":"(main)","a":"!==","b":"null","reason":"Use '!==' to compare with 'null'."},
{"id":"(error)","raw":"Use '{a}' to compare with '{b}'.","code":"W041","evidence":"              while (null != f)","line":254,"character":27,"scope":"(main)","a":"!==","b":"null","reason":"Use '!==' to compare with 'null'."},
{"id":"(error)","raw":"Use '{a}' to compare with '{b}'.","code":"W041","evidence":"          if (null != t.nodesbylevel[lp])","line":310,"character":20,"scope":"(main)","a":"!==","b":"null","reason":"Use '!==' to compare with 'null'."},
{"id":"(error)","raw":"Use '{a}' to compare with '{b}'.","code":"W041","evidence":"        if (null != nd)","line":344,"character":18,"scope":"(main)","a":"!==","b":"null","reason":"Use '!==' to compare with 'null'."},
{"id":"(error)","raw":"Use '{a}' to compare with '{b}'.","code":"W041","evidence":"              (null == end) || ","line":381,"character":21,"scope":"(main)","a":"===","b":"null","reason":"Use '===' to compare with 'null'."},
{"id":"(error)","raw":"Use '{a}' to compare with '{b}'.","code":"W041","evidence":"          while (null != gf)","line":422,"character":23,"scope":"(main)","a":"!==","b":"null","reason":"Use '!==' to compare with 'null'."},
{"id":"(error)","raw":"Use '{a}' to compare with '{b}'.","code":"W041","evidence":"        while (null != gf)","line":430,"character":21,"scope":"(main)","a":"!==","b":"null","reason":"Use '!==' to compare with 'null'."},
{"id":"(error)","raw":"Use '{a}' to compare with '{b}'.","code":"W041","evidence":"          if (null != n.father)","line":448,"character":20,"scope":"(main)","a":"!==","b":"null","reason":"Use '!==' to compare with 'null'."},
{"id":"(error)","raw":"Use '{a}' to compare with '{b}'.","code":"W041","evidence":"        if (null == tn)","line":457,"character":18,"scope":"(main)","a":"===","b":"null","reason":"Use '===' to compare with 'null'."},
{"id":"(error)","raw":"Use '{a}' to compare with '{b}'.","code":"W041","evidence":"        if (null != f)","line":463,"character":18,"scope":"(main)","a":"!==","b":"null","reason":"Use '!==' to compare with 'null'."},
{"id":"(error)","raw":"Use '{a}' to compare with '{b}'.","code":"W041","evidence":"            while (null != f)","line":468,"character":25,"scope":"(main)","a":"!==","b":"null","reason":"Use '!==' to compare with 'null'."},
{"id":"(error)","raw":"Use '{a}' to compare with '{b}'.","code":"W041","evidence":"          while (null != f)","line":476,"character":23,"scope":"(main)","a":"!==","b":"null","reason":"Use '!==' to compare with 'null'."},
{"id":"(error)","raw":"Use '{a}' to compare with '{b}'.","code":"W041","evidence":"        if ((null == tn) || (true === tn.putIntree))","line":528,"character":19,"scope":"(main)","a":"===","b":"null","reason":"Use '===' to compare with 'null'."},
{"id":"(error)","raw":"Use '{a}' to compare with '{b}'.","code":"W041","evidence":"              (null != nst) &&","line":540,"character":21,"scope":"(main)","a":"!==","b":"null","reason":"Use '!==' to compare with 'null'."},
{"id":"(error)","raw":"Use '{a}' to compare with '{b}'.","code":"W041","evidence":"            else if (null == tf)","line":548,"character":27,"scope":"(main)","a":"===","b":"null","reason":"Use '===' to compare with 'null'."},
{"id":"(error)","raw":"Use '{a}' to compare with '{b}'.","code":"W041","evidence":"        if (null == tf)","line":554,"character":18,"scope":"(main)","a":"===","b":"null","reason":"Use '===' to compare with 'null'."},
{"id":"(error)","raw":"Use '{a}' to compare with '{b}'.","code":"W041","evidence":"          if (null == this.isolates[nd[khop]])","line":556,"character":20,"scope":"(main)","a":"===","b":"null","reason":"Use '===' to compare with 'null'."},
{"id":"(error)","raw":"Use '{a}' to compare with '{b}'.","code":"W041","evidence":"        if (null != this.nodesbyid[ndid])","line":588,"character":18,"scope":"(main)","a":"!==","b":"null","reason":"Use '!==' to compare with 'null'."},
{"id":"(error)","raw":"Use '{a}' to compare with '{b}'.","code":"W041","evidence":"        if (null == t.nodesbylevel[t.nodes[lp][khop]])","line":654,"character":18,"scope":"(main)","a":"===","b":"null","reason":"Use '===' to compare with 'null'."},
{"id":"(error)","raw":"Use '{a}' to compare with '{b}'.","code":"W041","evidence":"        if (null == t.nodesbylevel[lpex])","line":684,"character":18,"scope":"(main)","a":"===","b":"null","reason":"Use '===' to compare with 'null'."},
{"id":"(error)","raw":"Use '{a}' to compare with '{b}'.","code":"W041","evidence":"      if (null == nd)","line":722,"character":16,"scope":"(main)","a":"===","b":"null","reason":"Use '===' to compare with 'null'."},
{"id":"(error)","raw":"Use '{a}' to compare with '{b}'.","code":"W041","evidence":"      if (null != nd.nodeInTree)","line":731,"character":16,"scope":"(main)","a":"!==","b":"null","reason":"Use '!==' to compare with 'null'."},
{"id":"(error)","raw":"Use '{a}' to compare with '{b}'.","code":"W041","evidence":"        while (null != tn.children[0])","line":741,"character":21,"scope":"(main)","a":"!==","b":"null","reason":"Use '!==' to compare with 'null'."},
{"id":"(error)","raw":"Use '{a}' to compare with '{b}'.","code":"W041","evidence":"        while (null != tn.brothers[0])","line":747,"character":21,"scope":"(main)","a":"!==","b":"null","reason":"Use '!==' to compare with 'null'."},
{"id":"(error)","raw":"Use '{a}' to compare with '{b}'.","code":"W041","evidence":"      if (null != this.nodesbyid[nd[kid]])","line":781,"character":16,"scope":"(main)","a":"!==","b":"null","reason":"Use '!==' to compare with 'null'."},
{"id":"(error)","raw":"Use '{a}' to compare with '{b}'.","code":"W041","evidence":"      if (null ==  this.nodesbylevel[nd[khop]])","line":789,"character":16,"scope":"(main)","a":"===","b":"null","reason":"Use '===' to compare with 'null'."},
{"id":"(error)","raw":"Use '{a}' to compare with '{b}'.","code":"W041","evidence":"        if (null == this.isolates[nd[khop]])","line":801,"character":18,"scope":"(main)","a":"===","b":"null","reason":"Use '===' to compare with 'null'."},
{"id":"(error)","raw":"Use '{a}' to compare with '{b}'.","code":"W041","evidence":"              (null != nst) && ","line":812,"character":21,"scope":"(main)","a":"!==","b":"null","reason":"Use '!==' to compare with 'null'."},
{"id":"(error)","raw":"Use '{a}' to compare with '{b}'.","code":"W041","evidence":"            else if (null == tmp)","line":822,"character":27,"scope":"(main)","a":"===","b":"null","reason":"Use '===' to compare with 'null'."},
{"id":"(error)","raw":"Use '{a}' to compare with '{b}'.","code":"W041","evidence":"        if (null == tmp)","line":828,"character":18,"scope":"(main)","a":"===","b":"null","reason":"Use '===' to compare with 'null'."},
{"id":"(error)","raw":"Use '{a}' to compare with '{b}'.","code":"W041","evidence":"          if (null == this.isolates[lv])","line":840,"character":20,"scope":"(main)","a":"===","b":"null","reason":"Use '===' to compare with 'null'."},
{"id":"(error)","raw":"Use '{a}' to compare with '{b}'.","code":"W041","evidence":"              (null != ned) && ","line":858,"character":21,"scope":"(main)","a":"!==","b":"null","reason":"Use '!==' to compare with 'null'."},
{"id":"(error)","raw":"Use '{a}' to compare with '{b}'.","code":"W041","evidence":"      if ((null != nst) && ","line":893,"character":17,"scope":"(main)","a":"!==","b":"null","reason":"Use '!==' to compare with 'null'."},
{"id":"(error)","raw":"Use '{a}' to compare with '{b}'.","code":"W041","evidence":"          (null != ned) &&","line":894,"character":17,"scope":"(main)","a":"!==","b":"null","reason":"Use '!==' to compare with 'null'."},
{"id":"(error)","raw":"Use '{a}' to compare with '{b}'.","code":"W041","evidence":"      if ((null != nst) && (null != ned) && (nst[khop] < ned[khop]) &&","line":925,"character":17,"scope":"(main)","a":"!==","b":"null","reason":"Use '!==' to compare with 'null'."},
{"id":"(error)","raw":"Use '{a}' to compare with '{b}'.","code":"W041","evidence":"      if ((null != nst) && (null != ned) && (nst[khop] < ned[khop]) &&","line":925,"character":34,"scope":"(main)","a":"!==","b":"null","reason":"Use '!==' to compare with 'null'."}
]
}
}